<core:FragmentDefinition xmlns="sap.m"
  xmlns:f="sap.f"
  xmlns:core="sap.ui.core">
  <VBox class="portlet portlet-box portlet-p02" tooltip="{tooltip}" busy="{busy}" busyIndicatorDelay="0">
    <customData>
      <core:CustomData key="portlet-id" value="{id}" writeToDom="true" />
    </customData>
    <layoutData>
      <f:GridContainerItemLayoutData rows="{height}" columns="{width}" />
    </layoutData>
    <HBox width="100%" class="portlet-header" visible="{= !${hideTitle} || ${switchable} }">
      <Title level="H2" text="{title}" visible="{= !${hideTitle} }" />
      <Text text="">
        <layoutData>
          <FlexItemData growFactor="1" />
        </layoutData>
      </Text>
      <Button icon="sap-icon://decline" type="Transparent" visible="{switchable}" class="icon-button portlet-close" press=".onPressClose" />
      <Button icon="sap-icon://add" type="Transparent" visible="{hasLink}" class="icon-button" press=".onPressLink" />
    </HBox>
    <ScrollContainer height="97%" vertical="true">
      <layoutData>
        <FlexItemData growFactor="1" />
      </layoutData>
      <HBox width="100%" height="2.0rem" justifyContent="Center" alignItems="Center" visible="{= ${listCount} === 0 }">
        <Text text="{i18n>MSG_00001}" />
      </HBox>
      <HBox width="100%" visible="{= ${listCount} &gt; 0 }">
        <VBox items="{list}" width="60%">
          <layoutData>
            <FlexItemData growFactor="1" />
          </layoutData>
          <HBox height="2.0rem" alignItems="Center">
            <Link text="{Title}" tooltip="{Title}" subtle="true" press=".onPressNoticeArticle">
              <layoutData>
                <FlexItemData maxWidth="100%" />
              </layoutData>
            </Link>
          </HBox>
        </VBox>
        <VBox items="{list}" width="24%">
          <HBox height="2.0rem" justifyContent="End" alignItems="Center">
            <Text text="{ path: 'Sdate', type: 'sap.ui.yesco.mvc.model.type.Date' }" wrapping="false" />
          </HBox>
        </VBox>
        <VBox items="{list}" width="14%" visible="{= ${newCount} &gt; 0 }">
          <HBox height="2.0rem" justifyContent="End" alignItems="Center">
            <Image src="asset/image/icon_new.png" tooltip="{i18n>LABEL_00105}" />
          </HBox>
        </VBox>
        <VBox items="{list}" width="14%" visible="{= ${importantCount} &gt; 0 }">
          <HBox height="2.0rem" justifyContent="End" alignItems="Center">
            <core:Icon src="sap-icon://notification" tooltip="{i18n>LABEL_00178}" size="1rem" color="{= ${Impor} === 'X' ? 'Default' : 'transparent' }" />
          </HBox>
        </VBox>
      </HBox>
    </ScrollContainer>
  </VBox>
</core:FragmentDefinition>